{
  "db_name": "PostgreSQL",
  "query": "SELECT * FROM users WHERE id = ANY($1) AND id != '00000000-0000-0000-0000-000000000000'",
  "describe": {
    "columns": [
      {
        "ordinal": 0,
        "name": "id",
        "type_info": "Uuid"
      },
      {
        "ordinal": 1,
        "name": "username",
        "type_info": "Varchar"
      },
      {
        "ordinal": 2,
        "name": "email",
        "type_info": "Varchar"
      },
      {
        "ordinal": 3,
        "name": "display_name",
        "type_info": "Varchar"
      },
      {
        "ordinal": 4,
        "name": "avatar_url",
        "type_info": "Varchar"
      },
      {
        "ordinal": 5,
        "name": "auth_source",
        "type_info": "Varchar"
      },
      {
        "ordinal": 6,
        "name": "created_at",
        "type_info": "Timestamptz"
      },
      {
        "ordinal": 7,
        "name": "updated_at",
        "type_info": "Timestamptz"
      },
      {
        "ordinal": 8,
        "name": "last_login",
        "type_info": "Timestamptz"
      },
      {
        "ordinal": 9,
        "name": "is_admin",
        "type_info": "Bool"
      },
      {
        "ordinal": 10,
        "name": "password_hash",
        "type_info": "Text"
      }
    ],
    "parameters": {
      "Left": [
        "UuidArray"
      ]
    },
    "nullable": [
      false,
      false,
      false,
      true,
      true,
      false,
      false,
      false,
      true,
      false,
      true
    ]
  },
  "hash": "dfd37b4c09b1d3faaada59c7092c6cdacb839b57d8adfd41d7b5bcaa7b61356c"
}
