{
  "db_name": "PostgreSQL",
  "query": "SELECT deployment_id, group_id FROM deployment_groups WHERE deployment_id = ANY($1)",
  "describe": {
    "columns": [
      {
        "ordinal": 0,
        "name": "deployment_id",
        "type_info": "Uuid"
      },
      {
        "ordinal": 1,
        "name": "group_id",
        "type_info": "Uuid"
      }
    ],
    "parameters": {
      "Left": [
        "UuidArray"
      ]
    },
    "nullable": [
      false,
      false
    ]
  },
  "hash": "7aedb57244cecece1565543171f1b5dc4e2979036f21564460a383036bc6adae"
}
